{
   "detail":{
      "id":"201612231001297020",
      "prospectId":"201612231001297020",
      "status":null,
      "entitlement":null,
      "prospectName":"Demo01",
      "leId":null,
      "prospectType":"0001",
      "domicileCountry":"AX",
      "prospectSegment":"N",
      "prospectSubSegment":"P8",
      "linkedGroup":"990222446 - 0THE OPTIONS CLEARING CORPORATION",
      "isic":"100",
      "prospectSource":"0001",
      "legalConstitution":"legal",
      "industry":null,
      "accountType":"0001",
      "tbSegment":null,
      "referredBy":"11066235-ANCIENT STEAMSHIP COMPANY LIMITED",
      "groupSalesTurnOver":"100",
      "lastUpdateUser":null,
      "lastUpdatedDate":"2016-12-23 20:11:30.019",
      "cddId":null,
      "groupId":null,
      "prospectOwner":null,
      "crmId":"1009000376",
      "isReFI":null,
      "isReFGO":null,
      "isNaturalPersons":false,
      "isPIV":false,
      "isBizBoundaries":false,
      "prospectTeamList":[

      ],
      "notes":[

      ],
      "actions":null,
      "enableInfo":false,
      "enableContact":false,
      "enableRCR":false,
      "enableDeals":false,
      "enableOnBoarding":false,
      "enableBCA":false,
      "viewInfo":false,
      "viewContact":false,
      "viewRCR":false,
      "viewDeals":false,
      "viewOnBoarding":false,
      "viewBCA":false,
      "contactDate":null,
      "rcrDate":null,
      "dealDate":null,
      "onBoardDate":null,
      "bcaDate":null,
      "owner":null,
      "dealId":null,
      "callReportId":null,
      "contactId":null,
      "bcaId":null,
      "onBoardId":null,
      "onBoardCount":0,
      "dealCount":0,
      "callReportCount":0,
      "contactCount":0,
      "bcaCount":0,
      "bcaStatus":null
   }
}
