{
  "offboarding/task/referback/category-account": {
    "id": 1,
    "success": true,
    "message": null,
    "uiServiceTokenID": null,
    "accountDetails": [
      {
        "accountUniqueId": "52739",
        "changeKey": "2272",
        "activityId": "OFB1043",
        "tpSystem": "HOGAN",
        "tpGroup": "Core Banking",
        "tpAccountNo": "15447-094-1726-0",
        "tpAccountName": "CUST NAME 27100872",
        "subProfileId": 1,
        "subProfileLocation": "FR",
        "organizationType": "HO",
        "action": null,
        "changeStatus": null,
        "tpXrefStatus": null,
        "accountTxnStatus": "OPEN",
        "uniqueKey": "2272",
        "id": "52739"
      },
      {
        "accountUniqueId": "52740",
        "changeKey": "2272",
        "activityId": "OFB1043",
        "tpSystem": "CADM",
        "tpGroup": "S2B",
        "tpAccountNo": "3333",
        "tpAccountName": "CUST NAME 30888045",
        "subProfileId": 1,
        "subProfileLocation": "FR",
        "organizationType": "HO",
        "action": null,
        "changeStatus": null,
        "tpXrefStatus": null,
        "accountTxnStatus": "OPEN",
        "uniqueKey": "2272",
        "id": "52740"
      },
      {
        "accountUniqueId": "52738",
        "changeKey": "2272",
        "activityId": "OFB1043",
        "tpSystem": "RMA",
        "tpGroup": "RMA",
        "tpAccountNo": "SCBLHKHH-BPOLPFTP",
        "tpAccountName": "CUST NAME 33225540",
        "subProfileId": 1,
        "subProfileLocation": "FR",
        "organizationType": "HO",
        "action": null,
        "changeStatus": null,
        "tpXrefStatus": null,
        "accountTxnStatus": "OPEN",
        "uniqueKey": "2272",
        "id": "52738"
      },
      {
        "accountUniqueId": "52741",
        "changeKey": "2272",
        "activityId": "OFB1043",
        "tpSystem": "WISE",
        "tpGroup": "S2B",
        "tpAccountNo": "27100872",
        "tpAccountName": "CUST NAME 33297191",
        "subProfileId": 1,
        "subProfileLocation": "FR",
        "organizationType": "HO",
        "action": null,
        "changeStatus": null,
        "tpXrefStatus": null,
        "accountTxnStatus": "OPEN",
        "uniqueKey": "2272",
        "id": "52741"
      }
    ],
    "caseDetail": {
      "activityId": "2542",
      "caseId": "116453",
      "caseType": "CDD",
      "categoryId": "1849",
      "clientId": 11025050,
      "version": "3",
      "closureStatus": "ACTIVE",
      "countryCode": "HK",
      "country": null,
      "revirewDateExtended": false,
      "currentCaseRenewalDate": 1562774400000,
      "extendedReviewDate": null,
      "cddType": null,
      "bookingLocation": "HK/SCHK",
      "caseClosureDate": null,
      "changeKey": "1840",
      "createdBy": "1490798",
      "createdDate": 1490600146000,
      "modifiedBy": null,
      "modifiedDate": null,
      "ownerRMId": "1494328",
      "ownerRMName": "Lam,Kit Ling",
      "ownerRMEmail": "Emily.Lam@sc.com",
      "uniqueKey": "1840",
      "id": "116453CDD2542"
    },
    "meta": {
      "totalRecords": 16
    }
  }
}