{
   "accountPlanTaskDetail":[
      {
         "customerName":"MTN GROUP LIMITED",
         "clientId":null,
         "groupId":"990034552",
         "segment":"GLOBAL CORPORATES",
         "subSegment":null,
         "domicileregion":"AFRICA",
         "industry":null,
         "incoporationCountry":null,
         "groupWebsite":null,
         "gamName":"Chiyangwa, Adelaide 1336261",
         "gamLocation":null,
         "tbSegment":"Network",
         "pfamName":null,
         "pfamLocation":null,
         "legalConstitution":null,
         "prospectId":null,
         "prospectOwner":null,
         "prospectOwnerLoc":null,
         "id":"990034552",
         "taskName":null,
         "taskAssignedBy":null,
         "taskDueDate":0,
         "taskAssignedDate":0,
         "taskId":null,
         "taskType":null,
         "notes":null,
         "inboxTaskId":null,
         "activityName":null,
         "taskStartDate":null,
         "taskAction":null,
         "taskAssignedTo":null,
         "activityId":null,
         "taskActionURL":null,
         "groupName":null,
         "incorporationCountry":null,
         "entityType":"G",
         "edit":true,
         "view":false,
         "initiate":false
      }
   ]
}
